adafruit_usb_host_mass_storage.py
adafruit_circuitpython_usb_host_mass_storage-0.8.4.dist-info/licenses/LICENSE
adafruit_circuitpython_usb_host_mass_storage-0.8.4.dist-info/METADATA
adafruit_circuitpython_usb_host_mass_storage-0.8.4.dist-info/WHEEL
adafruit_circuitpython_usb_host_mass_storage-0.8.4.dist-info/top_level.txt
adafruit_circuitpython_usb_host_mass_storage-0.8.4.dist-info/RECORD
