Metadata-Version: 2.4
Name: adafruit-circuitpython-usb-host-mass-storage
Version: 0.8.4
Summary: CircuitPython BlockDevice for USB mass storage devices
Author-email: Adafruit Industries <circuitpython@adafruit.com>
License: MIT
Project-URL: Homepage, https://github.com/adafruit/Adafruit_CircuitPython_USB_Host_Mass_Storage
Keywords: adafruit,blinka,circuitpython,micropython,usb-host-mass-storage,usb
Classifier: Intended Audience :: Developers
Classifier: Topic :: Software Development :: Libraries
Classifier: Topic :: Software Development :: Embedded Systems
Classifier: Topic :: System :: Hardware
Classifier: License :: OSI Approved :: MIT License
Classifier: Programming Language :: Python :: 3
License-File: LICENSE
Requires-Dist: Adafruit-Blinka
Requires-Dist: adafruit-circuitpython-usb-host-descriptors
Provides-Extra: optional
Dynamic: license-file
